desktop_2fa/__init__.py
desktop_2fa/app/__init__.py
desktop_2fa/app/clipboard.py
desktop_2fa/app/config.py
desktop_2fa/app/main.py
desktop_2fa/cli/__init__.py
desktop_2fa/cli/commands.py
desktop_2fa/cli/helpers.py
desktop_2fa/cli/importers.py
desktop_2fa/cli/main.py
desktop_2fa/cli/requirements.txt
desktop_2fa/crypto/__init__.py
desktop_2fa/crypto/aesgcm.py
desktop_2fa/crypto/argon2.py
desktop_2fa/totp/__init__.py
desktop_2fa/totp/generator.py
desktop_2fa/ui/__init__.py
desktop_2fa/ui/add_token_dialog.py
desktop_2fa/ui/main_window.py
desktop_2fa/ui/resources/__init__.py
desktop_2fa/utils/__init__.py
desktop_2fa/utils/time.py
desktop_2fa/vault/__init__.py
desktop_2fa/vault/models.py
desktop_2fa/vault/vault.py
desktop_2fa-0.7.3.dist-info/METADATA
desktop_2fa-0.7.3.dist-info/WHEEL
desktop_2fa-0.7.3.dist-info/entry_points.txt
desktop_2fa-0.7.3.dist-info/licenses/LICENSE
desktop_2fa-0.7.3.dist-info/licenses/NOTICE
desktop_2fa-0.7.3.dist-info/RECORD
