Metadata-Version: 2.4
Name: desktop-2fa
Version: 0.7.3
Summary: Secure offline 2FA desktop authenticator
Author: Łukasz Perek
License:                                  Apache License
License-File: LICENSE
License-File: NOTICE
Classifier: Programming Language :: Python :: 3
Classifier: Programming Language :: Python :: 3.11
Classifier: Programming Language :: Python :: 3.12
Classifier: Programming Language :: Python :: 3.13
Requires-Python: >=3.11
Requires-Dist: argon2-cffi>=23.1.0
Requires-Dist: cryptography>=42.0.0
Requires-Dist: pydantic>=2.0.0
Requires-Dist: rich>=13.0.0
Requires-Dist: typer>=0.9.0
Provides-Extra: dev
Requires-Dist: black>=24.0.0; extra == 'dev'
Requires-Dist: mypy>=1.0.0; extra == 'dev'
Requires-Dist: pytest-cov>=4.0.0; extra == 'dev'
Requires-Dist: pytest>=7.0; extra == 'dev'
Requires-Dist: ruff>=0.6.0; extra == 'dev'
